README.md
setup.cfg
setup.py
stringMLST.py
stringMLST.egg-info/PKG-INFO
stringMLST.egg-info/SOURCES.txt
stringMLST.egg-info/dependency_links.txt
stringMLST.egg-info/requires.txt
stringMLST.egg-info/top_level.txt