Metadata-Version: 2.1
Name: stringMLST
Version: 0.6.2
Summary: Fast k-mer based tool for alignment and assembly-free multi locus sequence typing (MLST) directly from genome sequencing reads.
Home-page: https://github.com/jordanlab/stringMLST
Author: Jordan Lab
Author-email: pypi@atc.io
License: UNKNOWN
Keywords: MLST,kmer,NGS,stringMSLT
Platform: UNKNOWN
Classifier: Programming Language :: Python :: 2.7
Classifier: Programming Language :: Python :: 3.5
